Metadata-Version: 2.4
Name: easyocr-digit
Version: 0.0.2
Summary: Minimal EasyOCR fork for digit recognition (CPU-only)
Home-page: https://github.com/IlyaRadinsky/easyocr
Download-URL: https://github.com/IlyaRadinsky/easyocr.git
Author: Ilya Radinsky
Author-email: radinsky.ilya@gmail.com
License: Apache License 2.0
Keywords: ocr optical character recognition deep learning neural network
Classifier: Development Status :: 5 - Production/Stable
License-File: LICENSE
Requires-Dist: torch==2.9.1
Requires-Dist: torchvision==0.24.1
Requires-Dist: opencv-python-headless
Requires-Dist: scipy
Requires-Dist: scikit-image==0.26.0
Requires-Dist: numpy
Requires-Dist: Pillow
Requires-Dist: PyYAML
Requires-Dist: pyclipper
Dynamic: author
Dynamic: author-email
Dynamic: classifier
Dynamic: description
Dynamic: description-content-type
Dynamic: download-url
Dynamic: home-page
Dynamic: keywords
Dynamic: license
Dynamic: license-file
Dynamic: requires-dist
Dynamic: summary
